gpt_code_interpreter/__init__.py
gpt_code_interpreter/agents/__init__.py
gpt_code_interpreter/agents/custom_agent.py
gpt_code_interpreter/agents/functions_agent.py
gpt_code_interpreter/chains/__init__.py
gpt_code_interpreter/chains/extract_code.py
gpt_code_interpreter/chains/modifications_check.py
gpt_code_interpreter/chains/rm_dl_link.py
gpt_code_interpreter/config.py
gpt_code_interpreter/prompts/__init__.py
gpt_code_interpreter/prompts/modifications_check.py
gpt_code_interpreter/prompts/remove_dl_link.py
gpt_code_interpreter/prompts/system_message.py
gpt_code_interpreter/schema/__init__.py
gpt_code_interpreter/schema/file.py
gpt_code_interpreter/schema/input.py
gpt_code_interpreter/schema/response.py
gpt_code_interpreter/session.py
gpt_code_interpreter/utils/__init__.py
gpt_code_interpreter/utils/callbacks.py
gpt_code_interpreter/utils/parser.py
gpt_code_interpreter-0.0.3.dist-info/LICENSE
gpt_code_interpreter-0.0.3.dist-info/METADATA
gpt_code_interpreter-0.0.3.dist-info/WHEEL
gpt_code_interpreter-0.0.3.dist-info/RECORD
