Metadata-Version: 2.1
Name: gpt-code-interpreter
Version: 0.0.3
Summary: CodeInterpreterAPI is an (unofficial) open source python interface for the ChatGPT CodeInterpreter.
License: MIT
Author: Shroominic
Author-email: contact@shroominic.com
Requires-Python: >=3.9, !=2.7.*, !=3.0.*, !=3.1.*, !=3.2.*, !=3.3.*, !=3.4.*, !=3.5.*, !=3.6.*, !=3.7.*, !=3.8.*
Classifier: License :: OSI Approved :: MIT License
Classifier: Programming Language :: Python :: 3
Classifier: Programming Language :: Python :: 3.9
Classifier: Programming Language :: Python :: 3.10
Classifier: Programming Language :: Python :: 3.11
Provides-Extra: all
Provides-Extra: frontend
Provides-Extra: image-support
Provides-Extra: localbox
Requires-Dist: codeboxapi (>=0.0.14,<0.0.15)
Requires-Dist: langchain (>=0.0.238,<0.0.239)
Requires-Dist: openai (>=0.27.8,<0.28.0)
Requires-Dist: python-dotenv (>=1.0.0,<2.0.0)
